fltower/__init__.py
fltower/__version__.py
fltower/data_manager.py
fltower/main_fltower.py
fltower/run_args.py
fltower/resource/__init__.py
fltower/resource/parameters.json
fltower-0.1.3.dist-info/LICENSE
fltower-0.1.3.dist-info/METADATA
fltower-0.1.3.dist-info/WHEEL
fltower-0.1.3.dist-info/entry_points.txt
fltower-0.1.3.dist-info/top_level.txt
fltower-0.1.3.dist-info/RECORD
