Metadata-Version: 2.1
Name: fltower
Version: 0.1.3
Summary: Software for cytometry analysis.
License: GNU GPL v3
License-File: LICENSE
Requires-Dist: numpy>=1.26.4
Requires-Dist: pandas>=2.2.3
Requires-Dist: matplotlib==3.9.2
Requires-Dist: seaborn==0.13.2
Requires-Dist: scipy==1.14.1
Requires-Dist: fcsparser==0.2.8
Requires-Dist: tqdm==4.67.1
